Ecarx_writeExcel/__init__.py
Ecarx_writeExcel/write_excel.py
Ecarx_writeExcel-1.0.dist-info/METADATA
Ecarx_writeExcel-1.0.dist-info/WHEEL
Ecarx_writeExcel-1.0.dist-info/top_level.txt
Ecarx_writeExcel-1.0.dist-info/RECORD
